deformable_gym/__init__.py
deformable_gym/assets/__init__.py
deformable_gym/assets/mj_scene_base.xml
deformable_gym/assets/__pycache__/__init__.cpython-312.pyc
deformable_gym/assets/meshes/insole.msh
deformable_gym/assets/meshes/pillow_small.msh
deformable_gym/assets/meshes/collision/robotiq/robotiq_ft300.STL
deformable_gym/assets/meshes/collision/robotiq/robotiq_fts150.stl
deformable_gym/assets/meshes/collision/robotiq/mountings/robotiq_ft300-G-062-COUPLING_G-50-4M6-1D6_20181119.STL
deformable_gym/assets/meshes/components/cable_connector/cable_connector_base_E3M5.dae
deformable_gym/assets/meshes/components/cable_connector/cable_connector_palm_E3M5.dae
deformable_gym/assets/meshes/components/f_distal/bt_2p/f_distal_bt_2p.dae
deformable_gym/assets/meshes/components/f_distal/bt_2p/f_distal_bt_2p_adapter.dae
deformable_gym/assets/meshes/components/f_distal/bt_sp/f_distal_bt_sp.dae
deformable_gym/assets/meshes/components/f_distal/pst/f_distal_pst.dae
deformable_gym/assets/meshes/components/f_knuckle/f_knuckle_C6M2.dae
deformable_gym/assets/meshes/components/f_knuckle/f_knuckle_E2M3.dae
deformable_gym/assets/meshes/components/f_knuckle/f_knuckle_E3M5.dae
deformable_gym/assets/meshes/components/f_knuckle/f_knuckle_G1M5.dae
deformable_gym/assets/meshes/components/f_middle/f_middle_C6M2.dae
deformable_gym/assets/meshes/components/f_middle/f_middle_E2M3.dae
deformable_gym/assets/meshes/components/f_middle/f_middle_E3M5.dae
deformable_gym/assets/meshes/components/f_middle/f_middle_G1M5.dae
deformable_gym/assets/meshes/components/f_proximal/f_proximal_C6M2.dae
deformable_gym/assets/meshes/components/f_proximal/f_proximal_E2M3.dae
deformable_gym/assets/meshes/components/f_proximal/f_proximal_E3M5.dae
deformable_gym/assets/meshes/components/f_proximal/f_proximal_G1M5.dae
deformable_gym/assets/meshes/components/forearm/forearm_C6M2.dae
deformable_gym/assets/meshes/components/forearm/forearm_E2M3.dae
deformable_gym/assets/meshes/components/forearm/forearm_E3M5.dae
deformable_gym-0.5.0.dist-info/licenses/LICENSE
deformable_gym-0.5.0.dist-info/METADATA
deformable_gym-0.5.0.dist-info/WHEEL
deformable_gym-0.5.0.dist-info/top_level.txt
deformable_gym-0.5.0.dist-info/RECORD
