Metadata-Version: 2.4
Name: deformable_gym
Version: 0.5.0
Summary: Gymnasium environments for grasping 3D deformable objects
Author-email: Melvin Laux <melvin.laux@uni-bremen.de>, Alexander Fabisch <alexander.fabisch@dfki.de>
Maintainer-email: Melvin Laux <melvin.laux@uni-bremen.de>
License-Expression: BSD-3-Clause
Project-URL: Homepage, https://github.com/dfki-ric/deformable_gym
Project-URL: Issues, https://github.com/dfki-ric/deformable_gym/issues
Keywords: Reinforcement Learning,Gymnasium,PyBullet,Mujoco
Classifier: Development Status :: 3 - Alpha
Classifier: Programming Language :: Python :: 3
Classifier: Programming Language :: Python :: 3.9
Classifier: Programming Language :: Python :: 3.10
Classifier: Programming Language :: Python :: 3.11
Classifier: Programming Language :: Python :: 3.12
Classifier: Intended Audience :: Science/Research
Classifier: Topic :: Scientific/Engineering :: Artificial Intelligence
Requires-Python: >=3.9
License-File: LICENSE
Requires-Dist: pybullet
Requires-Dist: gymnasium>=1.0.0a2
Requires-Dist: numpy>1.23.5
Requires-Dist: pytransform3d
Provides-Extra: dev
Requires-Dist: pytest; extra == "dev"
Requires-Dist: pre-commit; extra == "dev"
Requires-Dist: black; extra == "dev"
Requires-Dist: flake8; extra == "dev"
Requires-Dist: isort; extra == "dev"
Provides-Extra: mujoco
Requires-Dist: mujoco==3.2.3; extra == "mujoco"
Requires-Dist: imageio>=2.34.1; extra == "mujoco"
Provides-Extra: all
Requires-Dist: deformable_gym[dev,mujoco]; extra == "all"
Dynamic: license-file
